harmonizer/__init__.py
harmonizer/cli.py
harmonizer/config.py
harmonizer/enrichments.py
harmonizer/logme.ini
harmonizer/manipulations.py
harmonizer/validations.py
harmonizer-0.1.31.dist-info/LICENSE
harmonizer-0.1.31.dist-info/METADATA
harmonizer-0.1.31.dist-info/WHEEL
harmonizer-0.1.31.dist-info/entry_points.txt
harmonizer-0.1.31.dist-info/top_level.txt
harmonizer-0.1.31.dist-info/RECORD
