Metadata-Version: 2.1
Name: harmonizer
Version: 0.1.31
Summary: Harmonizes your audio media: converts, normalizes, enriches and validates.
Home-page: http://github.com/alafanechere/harmonizer
Author: Augustin Lafanechere
Author-email: augustin.lafanechere@gmail.com
License: GPLv3+
Platform: UNKNOWN
Classifier: Development Status :: 3 - Alpha
Classifier: License :: OSI Approved :: GNU General Public License v3 or later (GPLv3+)
Classifier: Programming Language :: Python :: 3.7
Classifier: Topic :: Multimedia :: Sound/Audio
Classifier: Topic :: Multimedia :: Sound/Audio :: Analysis
Classifier: Topic :: Multimedia :: Sound/Audio :: Editors
Classifier: Topic :: Multimedia :: Sound/Audio :: Conversion
Requires-Dist: eyeD3 (==0.8.10)
Requires-Dist: pydub (==0.23.1)
Requires-Dist: pyacoustid (==1.1.5)
Requires-Dist: mutagen (==1.42.0)
Requires-Dist: discogs-client (==2.2.2)
Requires-Dist: spotipy (==2.4.4)
Requires-Dist: titlecase (==0.12.0)
Requires-Dist: click (==7.0)
Requires-Dist: pyyaml (==5.1)
Requires-Dist: logme (==1.3.2)
Requires-Dist: schema (==0.7.0)
